Workbook

Sheet Assumptions
A1: OYA NODE PROPOSER FEE MODEL
A3: CORE ASSUMPTIONS | C3: Notes
A4: Monthly transactions | B4: 100000 | C4: Total proposals submitted per month
A5: OO Bond amount (USDC) | B5: 250 | C5: Per-proposal bond posted to Optimistic Oracle
A6: Challenge period (hours) | B6: 2 | C6: Time bond is locked per proposal
A7: Average trade size (USDC) | B7: 500 | C7: Average USDC value per copy-trade
A8: Gas cost per proposal (MATIC→USD) | B8: 0.02 | C8: Polygon L2 gas cost per tx
A9: Days in month | B9: 30
A10: Hours in day | B10: 24
A12: DERIVED METRICS
A13: Transactions per hour | B13: =B4/(B9*B10) -> 138.88889
A14: Transactions per day | B14: =B4/B9 -> 3333.3333
A15: Concurrent proposals (at any time) | B15: =B13*B6 -> 277.77778
A16: Capital locked in bonds at peak (USDC) | B16: =B15*B5 -> 69444.444
A17: Monthly gas costs (USD) | B17: =B4*B8 -> 2000

Sheet Fixed Fee Model
A1: FIXED FEE MODEL — Proposer charges flat fee per proposal
A3: FEE TIER COMPARISON
A4: Metric | B4: $0.25/proposal | C4: $0.50/proposal | D4: $1.00/proposal | E4: $2.00/proposal
A5: Fee per proposal (USDC) | B5: 0.25 | C5: 0.5 | D5: 1 | E5: 2
A6: Monthly revenue (USDC) | B6: =B5*Assumptions!B4 -> 25000 | C6: =C5*Assumptions!B4 -> 50000 | D6: =D5*Assumptions!B4 -> 100000 | E6: =E5*Assumptions!B4 -> 200000
A7: Monthly gas costs (USDC) | B7: =Assumptions!B17 -> 2000 | C7: =Assumptions!B17 -> 2000 | D7: =Assumptions!B17 -> 2000 | E7: =Assumptions!B17 -> 2000
A8: Net monthly revenue (USDC) | B8: =B6-B7 -> 23000 | C8: =C6-C7 -> 48000 | D8: =D6-D7 -> 98000 | E8: =E6-E7 -> 198000
A9: Capital required for bonds (USDC) | B9: =Assumptions!B16 -> 69444.444 | C9: =Assumptions!B16 -> 69444.444 | D9: =Assumptions!B16 -> 69444.444 | E9: =Assumptions!B16 -> 69444.444
A10: Monthly ROI on bond capital | B10: =B8/B9 -> 0.3312 | C10: =C8/C9 -> 0.6912 | D10: =D8/D9 -> 1.4112 | E10: =E8/E9 -> 2.8512
A11: Annualized ROI on bond capital | B11: =B10*12 -> 3.9744 | C11: =C10*12 -> 8.2944 | D11: =D10*12 -> 16.9344 | E11: =E10*12 -> 34.2144
A12: Fee as % of avg trade | B12: =B5/Assumptions!B7 -> 0.0005 | C12: =C5/Assumptions!B7 -> 0.001 | D12: =D5/Assumptions!B7 -> 0.002 | E12: =E5/Assumptions!B7 -> 0.004
A13: Break-even txns/month (gas only) | B13: =Assumptions!B17/B5 -> 8000 | C13: =Assumptions!B17/C5 -> 4000 | D13: =Assumptions!B17/D5 -> 2000 | E13: =Assumptions!B17/E5 -> 1000
A16: JOHN'S INSIGHT
A17: Fixed fee makes sense because the proposer's cost is the same
A18: whether it's a $10 trade or a $1,000,000 trade.
A19: The proposer's real costs: gas + opportunity cost of locked bond capital.

Sheet Variable Fee Model
A1: VARIABLE FEE MODEL — Proposer charges % of trade value
A3: FEE TIER COMPARISON
A4: Metric | B4: 0.05% | C4: 0.10% | D4: 0.25% | E4: 0.50%
A5: Fee rate | B5: 0.0005 | C5: 0.001 | D5: 0.0025 | E5: 0.005
A6: Fee per avg trade (USDC) | B6: =B5*Assumptions!B7 -> 0.25 | C6: =C5*Assumptions!B7 -> 0.5 | D6: =D5*Assumptions!B7 -> 1.25 | E6: =E5*Assumptions!B7 -> 2.5
A7: Monthly revenue (USDC) | B7: =B6*Assumptions!B4 -> 25000 | C7: =C6*Assumptions!B4 -> 50000 | D7: =D6*Assumptions!B4 -> 125000 | E7: =E6*Assumptions!B4 -> 250000
A8: Monthly gas costs (USDC) | B8: =Assumptions!B17 -> 2000 | C8: =Assumptions!B17 -> 2000 | D8: =Assumptions!B17 -> 2000 | E8: =Assumptions!B17 -> 2000
A9: Net monthly revenue (USDC) | B9: =B7-B8 -> 23000 | C9: =C7-C8 -> 48000 | D9: =D7-D8 -> 123000 | E9: =E7-E8 -> 248000
A10: Capital required for bonds (USDC) | B10: =Assumptions!B16 -> 69444.444 | C10: =Assumptions!B16 -> 69444.444 | D10: =Assumptions!B16 -> 69444.444 | E10: =Assumptions!B16 -> 69444.444
A11: Monthly ROI on bond capital | B11: =B9/B10 -> 0.3312 | C11: =C9/C10 -> 0.6912 | D11: =D9/D10 -> 1.7712 | E11: =E9/E10 -> 3.5712
A12: Annualized ROI on bond capital | B12: =B11*12 -> 3.9744 | C12: =C11*12 -> 8.2944 | D12: =D11*12 -> 21.2544 | E12: =E11*12 -> 42.8544
A13: Revenue at $100 avg trade | B13: =B5*100*Assumptions!B4 -> 5000 | C13: =C5*100*Assumptions!B4 -> 10000 | D13: =D5*100*Assumptions!B4 -> 25000 | E13: =E5*100*Assumptions!B4 -> 50000
A14: Revenue at $1,000 avg trade | B14: =B5*1000*Assumptions!B4 -> 50000 | C14: =C5*1000*Assumptions!B4 -> 100000 | D14: =D5*1000*Assumptions!B4 -> 250000 | E14: =E5*1000*Assumptions!B4 -> 500000
A15: Revenue at $10,000 avg trade | B15: =B5*10000*Assumptions!B4 -> 500000 | C15: =C5*10000*Assumptions!B4 -> 1000000 | D15: =D5*10000*Assumptions!B4 -> 2500000 | E15: =E5*10000*Assumptions!B4 -> 5000000
A18: TRADE-OFF
A19: Variable fee scales with trade size but penalizes large traders.
A20: A whale doing a $100K trade pays $250 at 0.25% — same as the bond itself.
A21: Small traders pay almost nothing, which may not cover gas.

Sheet Comparison
A1: FIXED vs VARIABLE — RECOMMENDATION
A3: SCENARIO: 100K txns/month
B4: Fixed ($0.50) | C4: Variable (0.10%) | D4: Winner
A5: Monthly gross revenue | B5: ='Fixed Fee Model'!C6 -> 50000 | C5: ='Variable Fee Model'!C7 -> 50000 | D5: =IF(B5>C5,"Fixed","Variable") -> Variable
A6: Monthly net revenue | B6: ='Fixed Fee Model'!C8 -> 48000 | C6: ='Variable Fee Model'!C9 -> 48000 | D6: =IF(B6>C6,"Fixed","Variable") -> Variable
A7: Revenue if avg trade = $100 | B7: ='Fixed Fee Model'!C6 -> 50000 | C7: ='Variable Fee Model'!C13 -> 10000 | D7: =IF(B7>C7,"Fixed","Variable") -> Fixed
A8: Revenue if avg trade = $1,000 | B8: ='Fixed Fee Model'!C6 -> 50000 | C8: ='Variable Fee Model'!C14 -> 100000 | D8: =IF(B8>C8,"Fixed","Variable") -> Variable
A9: Revenue if avg trade = $10,000 | B9: ='Fixed Fee Model'!C6 -> 50000 | C9: ='Variable Fee Model'!C15 -> 1000000 | D9: =IF(B9>C9,"Fixed","Variable") -> Variable
A10: Predictability | B10: High | C10: Low | D10: Fixed
A11: Fairness to large traders | B11: High | C11: Low | D11: Fixed
A12: Fairness to small traders | B12: Low | C12: High | D12: Variable
A13: Proposer risk | B13: Low | C13: Medium | D13: Fixed
A16: RECOMMENDATION
A17: Fixed fee of $0.50-$1.00 per proposal
A18: Reasoning:
A19: 1. Proposer costs are fixed (gas + bond capital) regardless of trade size
A20: 2. Predictable revenue — easy to forecast and scale infrastructure
A21: 3. Fair to whales — large traders aren't penalized with bigger fees
A22: 4. At $0.50/proposal with 100K txns: $50K/month net on ~$70K bond capital
A23: 5. That's ~71% monthly ROI / ~857% annualized on the bond capital
A24: 6. The bond is recycled every 2 hours so capital efficiency is very high
A26: CAPITAL EFFICIENCY NOTE
A27: The 250 USDC bond is NOT spent — it's returned after each challenge period.
A28: With 2hr challenge periods, each 250 USDC cycles ~12x per day.
A29: You only need enough bonds to cover CONCURRENT proposals, not total.
