Workbook

Sheet Assumptions
A1: OYA NODE PROPOSER — FULL BUSINESS MODEL
A3: TRANSACTION ASSUMPTIONS
A4: Complete trade cycles per month | B4: 50000 | C4: Each cycle = 1 agent trade copied
A5: Proposals per trade cycle | B5: 2 | C5: 1 reimbursement + 1 redemption/distribution
A6: Total proposals per month | B6: =B4*B5 -> 100000 | C6: This is the 100K number
A8: BOND & TIMING
A9: OO Bond amount (USDC) | B9: 250 | C9: Per proposal to Optimistic Oracle
A10: Challenge period (hours) | B10: 2 | C10: Time bond is locked
A11: Days in month | B11: 30
A12: Hours in day | B12: 24
A14: DERIVED — BOND CAPITAL NEEDS
A15: Proposals per hour | B15: =B6/(B11*B12) -> 138.88889
A16: Concurrent proposals at any time | B16: =B15*B10 -> 277.77778
A17: Bond capital locked at peak (USDC) | B17: =B16*B9 -> 69444.444
A18: Bond recycling per day (times) | B18: =B12/B10 -> 12 | C18: Each $250 is reused this many times/day
A20: FEE ASSUMPTIONS
A21: Fee per proposal (USDC) | B21: 0.5 | C21: Fixed fee — same for reimbursement & redemption
A22: Average trade size (USDC) | B22: 500 | C22: For reference only (fee is fixed)

Sheet Infrastructure Costs
A1: INFRASTRUCTURE COSTS — WHAT YOU ACTUALLY NEED
A3: KEY DIFFERENCE: OYA PROPOSER vs BLOCKCHAIN VALIDATOR
A4: Chorus One, Figment, etc. run full blockchain validators (Ethereum, Cosmos, Solana)
A5: requiring heavy hardware ($500-$4,000+/month). An Oya proposer node is a lightweight
A6: Node.js app that signs & submits transactions — similar to running a bot, not a validator.
A8: Component | B8: 100K proposals/mo | C8: 200K proposals/mo | D8: Notes
A9: VPS / Cloud Server | B9: 40 | C9: 80 | D9: Hetzner CPX31 or DigitalOcean $40-80/mo (4 vCPU, 8GB RAM)
A10: — Redundant backup server | B10: 40 | C10: 80 | D10: Second server for failover (recommended)
A11: Polygon RPC — Alchemy Growth | B11: 49 | C11: 99 | D11: Alchemy Growth $49/mo (40M CU); ~$99 for heavy usage
A12: — Backup RPC (Infura/Chainstack) | B12: 0 | C12: 50 | D12: Free tier as backup; paid at high volume
A13: IPFS Pinning — Pinata Picnic | B13: 20 | C13: 20 | D13: Pinata $20/mo (1TB storage, 500GB bandwidth)
A14: Domain + SSL | B14: 2 | C14: 2 | D14: Cloudflare free tier + $2/mo domain
A15: Monitoring (UptimeRobot/Grafana) | B15: 0 | C15: 15 | D15: Free tier at 100K; basic paid at 200K
A16: Gas costs (Polygon) | D16: Calculated below
A17: POLYGON GAS COSTS
A18: Gas per proposal tx (USD) | B18: 0.02 | C18: 0.02 | D18: Polygon avg gas ~$0.01-0.03 per tx
A19: Monthly gas cost (USD) | B19: =B18*Assumptions!B6 -> 2000 | C19: =C18*Assumptions!B6*2 -> 4000
A21: TOTAL MONTHLY INFRASTRUCTURE | B21: =SUM(B9:B15)+B19 -> 2151 | C21: =SUM(C9:C15)+C19 -> 4346
A23: FOR CONTEXT: TRADITIONAL VALIDATOR COSTS
A24: Ethereum validator (self-hosted) | B24: $175-400/mo | D24: 16GB RAM, 2TB SSD, dedicated hardware
A25: Ethereum validator (cloud) | B25: $500-2,000/mo | D25: AWS/GCP managed node services
A26: Solana validator | B26: $2,000-4,000+/mo | D26: 256GB RAM, high-perf NVMe, 10Gbps network
A27: Cosmos/Tendermint validator | B27: $200-800/mo | D27: Moderate hardware requirements
A28: Oya proposer node (YOU) | B28: ~$151-346/mo | D28: Lightweight Node.js — NOT a blockchain validator

Sheet P&L — 100K vs 200K
A1: MONTHLY P&L — PROPOSER NODE OPERATOR
B3: 100K Proposals/mo | C3: 200K Proposals/mo
A4: REVENUE
A5: Trade cycles | B5: =Assumptions!B4 -> 50000 | C5: =Assumptions!B4*2 -> 100000
A6: Proposals per cycle | B6: =Assumptions!B5 -> 2 | C6: =Assumptions!B5 -> 2
A7: Total proposals | B7: =B5*B6 -> 100000 | C7: =C5*C6 -> 200000
A8: Fee per proposal | B8: =Assumptions!B21 -> 0.5 | C8: =Assumptions!B21 -> 0.5
A9: GROSS REVENUE | B9: =B7*B8 -> 50000 | C9: =C7*C8 -> 100000
A11: COSTS
A12: Infrastructure (servers, RPC, IPFS) | B12: ='Infrastructure Costs'!B21 -> 2151 | C12: ='Infrastructure Costs'!C21 -> 4346
A13: Gas costs (included in infra) | B13: 0 | C13: 0
A14: TOTAL COSTS | B14: =B12+B13 -> 2151 | C14: =C12+C13 -> 4346
A16: PROFIT
A17: NET MONTHLY PROFIT | B17: =B9-B14 -> 47849 | C17: =C9-C14 -> 95654
A18: Net annual profit | B18: =B17*12 -> 574188 | C18: =C17*12 -> 1147848
A19: Profit margin | B19: =B17/B9 -> 0.95698 | C19: =C17/C9 -> 0.95654
A21: Bond capital required | B21: =Assumptions!B17 -> 69444.444 | C21: =Assumptions!B17*2 -> 138888.89
A22: Monthly ROI on bond capital | B22: =B17/B21 -> 0.6890256 | C22: =C17/C21 -> 0.6887088
A23: Annualized ROI on bond capital | B23: =B22*12 -> 8.2683072 | C23: =C22*12 -> 8.2645056
A25: Total capital needed (bonds + 3mo infra) | B25: =B21+B14*3 -> 75897.444 | C25: =C21+C14*3 -> 151926.89
A26: Monthly ROI on total capital | B26: =B17/B25 -> 0.63044283 | C26: =C17/C25 -> 0.62960547
A27: Payback period (months) | B27: =B25/B17 -> 1.5861866 | C27: =C25/C17 -> 1.5882962

Sheet Competitive Landscape
A1: CAN EXISTING NODE RUNNERS OUTCOMPETE YOU?
A3: SHORT ANSWER: Different business, different moat.
A5: Factor | B5: Chorus One / Figment | C5: Oya Proposer (You) | D5: Your Edge
A6: What they run | B6: Full blockchain validators | C6: Lightweight tx proposer | D6: 90% lower infra cost
A7: Monthly infra cost | B7: $500-$4,000+ | C7: ~$150-350 | D7: You're 10-20x cheaper to operate
A8: Capital requirement | B8: Millions (staked tokens) | C8: ~$70K (recycling bonds) | D8: Low barrier to entry
A9: Revenue model | B9: Staking rewards + MEV | C9: Per-proposal fixed fee | D9: Predictable, not market-dependent
A10: Hardware needs | B10: High-end servers, NVMe | C10: Basic VPS ($40/mo) | D10: Can run from laptop initially
A11: Network effect / moat | B11: Reputation + delegation | C11: Oya ecosystem integration | D11: First-mover in OG proposals
A12: Competition risk | B12: Crowded validator market | C12: New category (OG proposer) | D12: No direct competitors yet
A13: Scaling | B13: Need more hardware per chain | C13: Same node handles more volume | D13: Near-zero marginal cost
A16: WHY VALIDATORS CAN'T EASILY PIVOT TO THIS
A17: 1. Different protocol expertise — they know consensus, not OG/UMA verification
A18: 2. Their infra is optimized for block production, not lightweight tx submission
A19: 3. They need large delegations to be profitable; you need volume of proposals
A20: 4. The Oya proposer role is protocol-specific knowledge that takes time to build
A21: 5. Your real moat: deep integration with Oya agents + being first to market
